aiodispatch/__init__.py
aiodispatch/brokers/__init__.py
aiodispatch/brokers/abc.py
aiodispatch/brokers/memory.py
aiodispatch/decorators.py
aiodispatch/dispatch.py
aiodispatch/enums.py
aiodispatch/exceptions.py
aiodispatch/serializers/__init__.py
aiodispatch/serializers/abc.py
aiodispatch/serializers/json.py
aiodispatch/tasks.py
aiodispatch/types.py
aiodispatch/utils.py
aiodispatch/worker.py
aiodispatch-0.0.2.dist-info/LICENSE
aiodispatch-0.0.2.dist-info/METADATA
aiodispatch-0.0.2.dist-info/WHEEL
aiodispatch-0.0.2.dist-info/RECORD
