Metadata-Version: 2.1
Name: aiodispatch
Version: 0.0.2
Summary: 
Author: Niek Keijzer
Author-email: hello@niekkeijzer.com
Requires-Python: >=3.11,<4.0
Classifier: Programming Language :: Python :: 3
Classifier: Programming Language :: Python :: 3.11
